AUTHORS.rst
CHANGES.rst
COPYING.LGPLv3
MANIFEST.in
README.rst
setup.py
django_form_admin.egg-info/PKG-INFO
django_form_admin.egg-info/SOURCES.txt
django_form_admin.egg-info/dependency_links.txt
django_form_admin.egg-info/not-zip-safe
django_form_admin.egg-info/top_level.txt
formadmin/__init__.py
formadmin/forms.py
formadmin/templates/formadmin/form_admin_django.html
formadmin/templatetags/__init__.py
formadmin/templatetags/formadmin_filters.py