Metadata-Version: 1.1
Name: django-form-admin
Version: 0.4.2
Summary: Abstract class implemented to provide form django admin like
Home-page: https://github.com/Yaco-Sistemas/django-form-admin
Author: Pablo Martin
Author-email: goinnn@gmail.com
License: LGPL 3
Keywords: django,admin form,form admin,admin,form,render
Platform: UNKNOWN
Classifier: Development Status :: 4 - Beta
Classifier: Framework :: Django
Classifier: License :: OSI Approved :: GNU Library or Lesser General Public License (LGPL)
Classifier: Programming Language :: Python :: 2
Classifier: Programming Language :: Python :: 3
